mehtap/__init__.py
mehtap/__main__.py
mehtap/ast_nodes.py
mehtap/ast_transformer.py
mehtap/control_structures.py
mehtap/global_table.py
mehtap/library/provider_abc.py
mehtap/library/stdlib/basic_library.py
mehtap/library/stdlib/io_library.py
mehtap/library/stdlib/os_library.py
mehtap/library/stdlib/table_library.py
mehtap/lua.lark
mehtap/lua2py.py
mehtap/operations.py
mehtap/parser.py
mehtap/py2lua.py
mehtap/scope.py
mehtap/values.py
mehtap/vm.py
mehtap-0.2.0.dist-info/LICENSE
mehtap-0.2.0.dist-info/METADATA
mehtap-0.2.0.dist-info/WHEEL
mehtap-0.2.0.dist-info/entry_points.txt
mehtap-0.2.0.dist-info/RECORD
