Metadata-Version: 2.3
Name: mehtap
Version: 0.2.0
Summary: Lua programming language written in Python
License: MIT
Keywords: lua,parser,interpreter
Author: Emre Özcan
Author-email: emre@emreis.com
Requires-Python: >=3.10
Classifier: Development Status :: 4 - Beta
Classifier: Environment :: Console
Classifier: Intended Audience :: Developers
Classifier: License :: OSI Approved :: MIT License
Classifier: Operating System :: OS Independent
Classifier: Programming Language :: Lua
Classifier: Programming Language :: Python :: 3
Classifier: Programming Language :: Python :: 3.10
Classifier: Programming Language :: Python :: 3.11
Classifier: Programming Language :: Python :: 3.12
Classifier: Programming Language :: Python :: 3.13
Classifier: Topic :: Software Development :: Interpreters
Classifier: Topic :: Software Development :: Libraries
Requires-Dist: attrs (>=24.2.0,<25.0.0)
Requires-Dist: lark (>=1.2.2,<2.0.0)
Requires-Dist: prompt-toolkit (>=3.0.51,<4.0.0)
Project-URL: Documentation, https://mehtap.readthedocs.io/en/latest/
Project-URL: Repository, https://github.com/emreozcan/mehtap
